README.txt
setup.py
siya_rama.py
siya_rama.egg-info/PKG-INFO
siya_rama.egg-info/SOURCES.txt
siya_rama.egg-info/dependency_links.txt
siya_rama.egg-info/top_level.txt