Metadata-Version: 2.2
Name: siya_rama
Version: 1.2
Summary: The module have function to search for letters in string passed
Author: SnehaK
Dynamic: author
Dynamic: summary
